{
  "network": "Rise Testnet",
  "chainId": 11155931,
  "deployer": "0x004566C322f5F1CBC0594928556441f8D38EA589",
  "timestamp": "2026-03-29T18:54:54.368Z",
  "contracts": {
    "tokens": {
      "WETH": {
        "address": "0x0234367975aCbcBe49867dD36bf37C7d05C2E743",
        "name": "Wrapped Ether",
        "decimals": 18,
        "price": 1996.51
      },
      "USDC": {
        "address": "0x1B40c25A7cDF5b11c67dc956d6b63EEaE1C349B0",
        "name": "USD Coin",
        "decimals": 6,
        "price": 0.999787
      },
      "USDT": {
        "address": "0xa95558713D7E6D3F41bC70E867323A84404586f9",
        "name": "Tether USD",
        "decimals": 6,
        "price": 0.999191
      },
      "WBTC": {
        "address": "0xD35648Ad048e450aFd22f3421cE6A5EFFC40DC4D",
        "name": "Wrapped Bitcoin",
        "decimals": 8,
        "price": 66394
      },
      "DAI": {
        "address": "0x51A046A489da585eB5875845FdC7323c0f1F0606",
        "name": "Dai Stablecoin",
        "decimals": 18,
        "price": 0.999989
      }
    },
    "shards": {
      "WETH-USDC": [
        {
          "address": "0x1BdBf2fD483633f7BB5Bf34E94E80fF550D3c6b9",
          "name": "WETH-USDC-Small",
          "liquidityUSD": 250000,
          "amountA": "62.60925314674106368",
          "amountB": "125026.630672",
          "managedByOrchestrator": true
        },
        {
          "address": "0x608a9344f86Df1c357649210CC5cDb8c84514e18",
          "name": "WETH-USDC-Medium",
          "liquidityUSD": 1000000,
          "amountA": "250.43701258696425472",
          "amountB": "500106.522689",
          "managedByOrchestrator": true
        },
        {
          "address": "0xB74a9215D920d3151950D5006571d37b9531639c",
          "name": "WETH-USDC-Large",
          "liquidityUSD": 5000000,
          "amountA": "1252.185062934821208064",
          "amountB": "2500532.613446",
          "managedByOrchestrator": true
        },
        {
          "address": "0x07Dca56eA3377C04295f7A835225c86fc968d347",
          "name": "WETH-USDC-Small-Dynamic",
          "liquidityUSD": 250000,
          "amountA": "62.426960456266172628",
          "amountB": "125023.004233",
          "createdBy": "DynamicShardManager",
          "createdAt": "2026-03-29T20:41:31.321Z",
          "managedByOrchestrator": true
        }
      ],
      "USDC-USDT": [
        {
          "address": "0x16C8E409ab7aaAD129B342b2fC5e78725e5Be424",
          "name": "USDC-USDT-Small",
          "liquidityUSD": 250000,
          "amountA": "125026.630672",
          "amountB": "125101.206876",
          "managedByOrchestrator": true
        },
        {
          "address": "0xB3dc8a84a56Cc13b4A8A5FDc0586d4093C0f9209",
          "name": "USDC-USDT-Medium",
          "liquidityUSD": 1000000,
          "amountA": "500106.522689",
          "amountB": "500404.827505",
          "managedByOrchestrator": true
        },
        {
          "address": "0x91652d0c178a24C4149329d120635DBd8F2edF57",
          "name": "USDC-USDT-Large",
          "liquidityUSD": 5000000,
          "amountA": "2500532.613446",
          "amountB": "2502024.137527",
          "managedByOrchestrator": true
        },
        {
          "address": "0xaEe1aa8AC23c12b1A4db1E0E1F6EEc5BAc72368e",
          "name": "USDC-USDT-Small-Dynamic",
          "liquidityUSD": 250000,
          "amountA": "125023.504419",
          "amountB": "125098.202089",
          "createdBy": "DynamicShardManager",
          "createdAt": "2026-03-29T20:42:32.472Z",
          "managedByOrchestrator": true
        }
      ],
      "WETH-USDT": [
        {
          "address": "0x6bf53263ad782621aE7DaAE8557EBA21B102acfB",
          "name": "WETH-USDT-Small",
          "liquidityUSD": 250000,
          "amountA": "62.60925314674106368",
          "amountB": "125101.206876",
          "managedByOrchestrator": true
        },
        {
          "address": "0x6EE03cF6eBaE2b2b9ea738DDd6C12e2F8461279c",
          "name": "WETH-USDT-Medium",
          "liquidityUSD": 1000000,
          "amountA": "250.43701258696425472",
          "amountB": "500404.827505",
          "managedByOrchestrator": true
        },
        {
          "address": "0x7be7aA7974cC8a61def836cBAF4FB25d14247EEc",
          "name": "WETH-USDT-Large",
          "liquidityUSD": 5000000,
          "amountA": "1252.185062934821208064",
          "amountB": "2502024.137527",
          "managedByOrchestrator": true
        },
        {
          "address": "0xb5C4c1D6C7c1e40d92203C9E5e58fEb4058731e8",
          "name": "WETH-USDT-Small-Dynamic",
          "liquidityUSD": 250000,
          "amountA": "62.439745645452134681",
          "amountB": "125098.202089",
          "createdBy": "DynamicShardManager",
          "createdAt": "2026-03-29T20:42:37.847Z",
          "managedByOrchestrator": true
        }
      ],
      "WBTC-USDC": [
        {
          "address": "0xf5660c5d7955dCc112F9361BD5BA70749B5e5a1d",
          "name": "WBTC-USDC-Small",
          "liquidityUSD": 250000,
          "amountA": "1.88270024",
          "amountB": "125026.630672",
          "managedByOrchestrator": true
        },
        {
          "address": "0x9fE6DaF022786f18369569D14d88034777D5CFF6",
          "name": "WBTC-USDC-Medium",
          "liquidityUSD": 1000000,
          "amountA": "7.53080097",
          "amountB": "500106.522689",
          "managedByOrchestrator": true
        },
        {
          "address": "0x3A741420322E3AA54fCCE2Dff15b4f4e242eF7D3",
          "name": "WBTC-USDC-Large",
          "liquidityUSD": 5000000,
          "amountA": "37.65400487",
          "amountB": "2500532.613446",
          "managedByOrchestrator": true
        },
        {
          "address": "0x30Cef3E3bc4A79E39371c46255e2e12791347393",
          "name": "WBTC-USDC-Small-Dynamic",
          "liquidityUSD": 250000,
          "amountA": "1.8767078",
          "amountB": "125023.504419",
          "createdBy": "DynamicShardManager",
          "createdAt": "2026-03-29T20:42:43.089Z",
          "managedByOrchestrator": true
        }
      ],
      "USDC-DAI": [
        {
          "address": "0x3932ecc1e7A6C350948b3A966CCed8Fbc51e9420",
          "name": "USDC-DAI-Small",
          "liquidityUSD": 250000,
          "amountA": "125026.630672",
          "amountB": "125001.375015125158723584",
          "managedByOrchestrator": true
        },
        {
          "address": "0x455Db509Ae3474B21abEBf4ddE3350Ea16b22700",
          "name": "USDC-DAI-Medium",
          "liquidityUSD": 1000000,
          "amountA": "500106.522689",
          "amountB": "500005.500060500634894336",
          "managedByOrchestrator": true
        },
        {
          "address": "0xb33f4AE4DcCd648eFA230719f7325B0cc39c78F0",
          "name": "USDC-DAI-Large",
          "liquidityUSD": 5000000,
          "amountA": "2500532.613446",
          "amountB": "2500027.500302503442907136",
          "managedByOrchestrator": true
        },
        {
          "address": "0x3303B990798521226981f7c1f60BcC8557651DFd",
          "name": "USDC-DAI-Small-Dynamic",
          "liquidityUSD": 250000,
          "amountA": "125023.504419",
          "amountB": "125037.76140394399408251",
          "createdBy": "DynamicShardManager",
          "createdAt": "2026-03-29T20:42:48.576Z",
          "managedByOrchestrator": true
        }
      ]
    },
    "factory": "0xc4c6ceABeBBfA1Bf9D219fE80F5b95982664fb94",
    "router": "0x6A45347a8DbC629000F725c544D695209b0c3d00",
    "orchestrator": "0x93174f86F57A97827680c279e07704AbE2a0b0c0",
    "faucet": "0x42a930BF9259cE3D9e76bb1d8C61b52daf68dBE4"
  },
  "poolStats": {
    "totalShards": 15,
    "totalLiquidityUSD": 31250000
  },
  "marketPrices": {
    "WETH": 1996.51,
    "USDC": 0.999787,
    "USDT": 0.999191,
    "WBTC": 66394,
    "DAI": 0.999989,
    "fetchedAt": "2026-03-29T18:54:58.216Z"
  },
  "swapLog": [
    {
      "label": "WETH-USDC A→B small",
      "direction": "WETH→USDC",
      "mode": "router",
      "amountOut": "100.0",
      "amountIn": "0.050108782663804448",
      "rate": "1995.65813983",
      "shardTier": "WETH-USDC-Large",
      "txHash": "0xa4bc95be4a499a5909e6a1a68583b3195dfa0d9f675978aede71b771db81878e"
    },
    {
      "label": "WETH-USDC B→A small",
      "direction": "USDC→WETH",
      "mode": "router",
      "amountOut": "0.01",
      "amountIn": "20.027818",
      "rate": "0.00049931",
      "shardTier": "WETH-USDC-Large",
      "txHash": "0xad7ffeba612d6a446f2b8ed45a231f43bb6f64b013d6ea266db907e78281ec42"
    },
    {
      "label": "WETH-USDC A→B medium",
      "direction": "WETH→USDC",
      "mode": "router",
      "amountOut": "5000.0",
      "amountIn": "2.510516496493537617",
      "rate": "1991.62204550",
      "shardTier": "WETH-USDC-Large",
      "txHash": "0xd89e2855b73d04deb120cf8291ab3cf20eabe51cb95e353850fe34ef896f6a9b"
    },
    {
      "label": "WETH-USDC B→A medium",
      "direction": "USDC→WETH",
      "mode": "router",
      "amountOut": "0.5",
      "amountIn": "997.793333",
      "rate": "0.00050111",
      "shardTier": "WETH-USDC-Large",
      "txHash": "0xa2b37d06986eb856b81310f164b59d400368c0dde3049740b8e2826f280dec8e"
    },
    {
      "label": "USDC-USDT A→B small",
      "direction": "USDC→USDT",
      "mode": "router",
      "amountOut": "100.0",
      "amountIn": "100.243303",
      "rate": "0.99757288",
      "shardTier": "USDC-USDT-Large",
      "txHash": "0xca1c4efaca12f196e59b46592b75d73349f3ad64d71cb1cd90d4d01b1a512979"
    },
    {
      "label": "USDC-USDT B→A small",
      "direction": "USDT→USDC",
      "mode": "router",
      "amountOut": "100.0",
      "amountIn": "100.354893",
      "rate": "0.99646362",
      "shardTier": "USDC-USDT-Large",
      "txHash": "0x752546df4c6b0e260a58df65f87efe28b7d31db77727891e72a74c03355e8a1f"
    },
    {
      "label": "USDC-USDT A→B medium",
      "direction": "USDC→USDT",
      "mode": "router",
      "amountOut": "5000.0",
      "amountIn": "5019.522634",
      "rate": "0.99611066",
      "shardTier": "USDC-USDT-Large",
      "txHash": "0x3e705f291e3b0297f6243061823ceb189a32aa72a89082db6451dd070f6b37b9"
    },
    {
      "label": "USDC-USDT B→A medium",
      "direction": "USDT→USDC",
      "mode": "router",
      "amountOut": "5000.0",
      "amountIn": "5005.403239",
      "rate": "0.99892052",
      "shardTier": "USDC-USDT-Large",
      "txHash": "0xf89825dc4aa631a3074dce2de87205e0810829f1b97d630baa85a8ec5ee1d044"
    },
    {
      "label": "WETH-USDT A→B small",
      "direction": "WETH→USDT",
      "mode": "router",
      "amountOut": "100.0",
      "amountIn": "0.050078910273550678",
      "rate": "1996.84856267",
      "shardTier": "WETH-USDT-Large",
      "txHash": "0x1b28ff8352313026d5e02e3d141423be5c70df342232ad21c8e888e6a4236ef9"
    },
    {
      "label": "WETH-USDT B→A small",
      "direction": "USDT→WETH",
      "mode": "router",
      "amountOut": "0.01",
      "amountIn": "20.039765",
      "rate": "0.00049901",
      "shardTier": "WETH-USDT-Large",
      "txHash": "0xff169faa3628ce59bc8b363426a029e095ba7c38fae38c8b4c389d106cc938a0"
    },
    {
      "label": "WETH-USDT A→B medium",
      "direction": "WETH→USDT",
      "mode": "router",
      "amountOut": "5000.0",
      "amountIn": "2.509016795054244905",
      "rate": "1992.81248729",
      "shardTier": "WETH-USDT-Large",
      "txHash": "0x8966d82caad31315f6457fea330d75a061b00b0c80357877daf8537e6ea7b45e"
    },
    {
      "label": "WETH-USDT B→A medium",
      "direction": "USDT→WETH",
      "mode": "router",
      "amountOut": "0.5",
      "amountIn": "998.390933",
      "rate": "0.00050081",
      "shardTier": "WETH-USDT-Large",
      "txHash": "0x7174bf1e843d8a80f5881b2269d2c2f770b281a2c08b9830fd03534eda67ef3c"
    },
    {
      "label": "WBTC-USDC A→B small",
      "direction": "WBTC→USDC",
      "mode": "router",
      "amountOut": "100.0",
      "amountIn": "0.0015068",
      "rate": "66365.80833555",
      "shardTier": "WBTC-USDC-Large",
      "txHash": "0x364f7a5c9117c25d56101fc924bb5ed928148b968e58bde0f68e5e58df4a2e10"
    },
    {
      "label": "WBTC-USDC B→A small",
      "direction": "USDC→WBTC",
      "mode": "router",
      "amountOut": "0.001",
      "amountIn": "66.603803",
      "rate": "0.00001501",
      "shardTier": "WBTC-USDC-Large",
      "txHash": "0xbab2f69a11073e2d246ca02585d5d65ba6bb079b7be8ca9096cd62efacbc0064"
    },
    {
      "label": "WBTC-USDC A→B medium",
      "direction": "WBTC→USDC",
      "mode": "router",
      "amountOut": "5000.0",
      "amountIn": "0.07549002",
      "rate": "66233.92072224",
      "shardTier": "WBTC-USDC-Large",
      "txHash": "0x0ca3a635bacc54ce23b615ee6a8651585ceebaa3f2e7271a9b08fd6922f40335"
    },
    {
      "label": "WBTC-USDC B→A medium",
      "direction": "USDC→WBTC",
      "mode": "router",
      "amountOut": "0.02",
      "amountIn": "1327.489596",
      "rate": "0.00001507",
      "shardTier": "WBTC-USDC-Large",
      "txHash": "0x6a9316d8c91fd70438b4e40fc704097fb791b3b4323ee574cd4fbfed6bd695f3"
    },
    {
      "label": "USDC-DAI A→B small",
      "direction": "USDC→DAI",
      "mode": "router",
      "amountOut": "100.0",
      "amountIn": "100.323365",
      "rate": "0.99677677",
      "shardTier": "USDC-DAI-Large",
      "txHash": "0xca2fdcf43089e8d80c52e92584b88507e6a0c5f21851fad5688ef382f073adb5"
    },
    {
      "label": "USDC-DAI B→A small",
      "direction": "DAI→USDC",
      "mode": "router",
      "amountOut": "100.0",
      "amountIn": "100.274703352258861645",
      "rate": "0.99726049",
      "shardTier": "USDC-DAI-Large",
      "txHash": "0x02888042a2c72739af7251b62b7426d949d3519fc085a18d0204f22958722cb4"
    },
    {
      "label": "USDC-DAI A→B medium",
      "direction": "USDC→DAI",
      "mode": "router",
      "amountOut": "5000.0",
      "amountIn": "5023.539792",
      "rate": "0.99531410",
      "shardTier": "USDC-DAI-Large",
      "txHash": "0x88f32697d64a56c09459385da22b5645c402a650642bbf5fe6913fd8b58b05dd"
    },
    {
      "label": "USDC-DAI B→A medium",
      "direction": "DAI→USDC",
      "mode": "router",
      "amountOut": "5000.0",
      "amountIn": "5001.39253076994869841",
      "rate": "0.99972157",
      "shardTier": "USDC-DAI-Large",
      "txHash": "0x01dfacfff0b8d22956629903f78d217fb4fea29c301fe5608d173f790f823abb"
    },
    {
      "label": "Direct WETH→USDC on WETH-USDC-Small",
      "direction": "WETH→USDC",
      "mode": "direct",
      "amountOut": "50.0",
      "amountIn": "0.025063407190110961",
      "rate": "1994.94025775",
      "feePct": "0.0599",
      "shardName": "WETH-USDC-Small",
      "txHash": "0xdc4fe1d5f432311e1beb62efca0d5ab3147c0c72269d97cc9307a724e744f901"
    },
    {
      "label": "Direct USDC→WETH on WETH-USDC-Small",
      "direction": "USDC→WETH",
      "mode": "direct",
      "amountOut": "0.005",
      "amountIn": "10.007416",
      "rate": "0.00049963",
      "feePct": "0.2991",
      "shardName": "WETH-USDC-Small",
      "txHash": "0x45542f8acc4f57ebe38e99e82f9aad6245d28ef9f87a286a86a056daf015d66e"
    },
    {
      "label": "Direct USDC→USDT on USDC-USDT-Small",
      "direction": "USDC→USDT",
      "mode": "direct",
      "amountOut": "50.0",
      "amountIn": "50.135137",
      "rate": "0.99730455",
      "feePct": "0.2891",
      "shardName": "USDC-USDT-Small",
      "txHash": "0xa23f60fe8ea4d643d9945c5ff47f323776fcbc0b539fa9accd20493725d3bb1d"
    },
    {
      "label": "Direct USDT→USDC on USDC-USDT-Small",
      "direction": "USDT→USDC",
      "mode": "direct",
      "amountOut": "50.0",
      "amountIn": "50.154794",
      "rate": "0.99691367",
      "feePct": "0.2891",
      "shardName": "USDC-USDT-Small",
      "txHash": "0x39821f0df069b590e2441775731577601d22b463e62f151da6af21d5a7202c1d"
    },
    {
      "label": "Direct WETH→USDT on WETH-USDT-Small",
      "direction": "WETH→USDT",
      "mode": "direct",
      "amountOut": "50.0",
      "amountIn": "0.0250484602466431",
      "rate": "1996.13068060",
      "feePct": "0.0599",
      "shardName": "WETH-USDT-Small",
      "txHash": "0x426370bbda359d7d3b57bed78191595e5edd60c1f679c007cdb387a680616e26"
    },
    {
      "label": "Direct USDT→WETH on WETH-USDT-Small",
      "direction": "USDT→WETH",
      "mode": "direct",
      "amountOut": "0.005",
      "amountIn": "10.01339",
      "rate": "0.00049933",
      "feePct": "0.2991",
      "shardName": "WETH-USDT-Small",
      "txHash": "0xc4b7a77d9f38a2aacdf523a1758a560fef32960cf241617507c9d763a8572095"
    },
    {
      "label": "Direct WBTC→USDC on WBTC-USDC-Small",
      "direction": "WBTC→USDC",
      "mode": "direct",
      "amountOut": "50.0",
      "amountIn": "0.00075367",
      "rate": "66342.03298526",
      "feePct": "0.0584",
      "shardName": "WBTC-USDC-Small",
      "txHash": "0xb7e1355df279e1a2ee81c8041b4288904a7fc37c37e3daa609d4686bcfe8188c"
    },
    {
      "label": "Direct USDC→WBTC on WBTC-USDC-Small",
      "direction": "USDC→WBTC",
      "mode": "direct",
      "amountOut": "0.0005",
      "amountIn": "33.285854",
      "rate": "0.00001502",
      "feePct": "0.2990",
      "shardName": "WBTC-USDC-Small",
      "txHash": "0x2e4a1b275e45446fed3d7acd74d740bd7d7214b0ac7cec0d54870c06127c6327"
    },
    {
      "label": "Direct USDC→DAI on USDC-DAI-Small",
      "direction": "USDC→DAI",
      "mode": "direct",
      "amountOut": "50.0",
      "amountIn": "50.175193",
      "rate": "0.99650837",
      "feePct": "0.2891",
      "shardName": "USDC-DAI-Small",
      "txHash": "0xbaee8800ab497755f96398e5eb42fd36237849676daa9bb488f476cfd61c9563"
    },
    {
      "label": "Direct DAI→USDC on USDC-DAI-Small",
      "direction": "DAI→USDC",
      "mode": "direct",
      "amountOut": "50.0",
      "amountIn": "50.114688718589323989",
      "rate": "0.99771147",
      "feePct": "0.2890",
      "shardName": "USDC-DAI-Small",
      "txHash": "0x27652a803fe6d4a55b5fd8ced61060c5a00cf1a0e844238239dae8a18374b96c"
    },
    {
      "label": "WBTC→USDC→USDT",
      "direction": "WBTC→USDC→USDT",
      "mode": "multi-hop",
      "amountOut": "4500.0",
      "amountIn": "0.06838436",
      "rate": "65804.52021486",
      "shardTiers": [
        "WBTC-USDC-Large",
        "USDC-USDT-Large"
      ],
      "txHash": "0xa715f521282d5ae1f840962811b3149499f685b82c10aa7bde7c4b2c5bd49570"
    },
    {
      "label": "USDT→USDC→WBTC",
      "direction": "USDT→USDC→WBTC",
      "mode": "multi-hop",
      "amountOut": "0.005",
      "amountIn": "330.918971",
      "rate": "0.00001511",
      "shardTiers": [
        "USDC-USDT-Large",
        "WBTC-USDC-Large"
      ],
      "txHash": "0x823f2c809568d6e7f4b8418af5bd9d1895e8b1fa57284258486812bb20cbc954"
    },
    {
      "label": "WETH→USDC→DAI",
      "direction": "WETH→USDC→DAI",
      "mode": "multi-hop",
      "amountOut": "3500.0",
      "amountIn": "1.769475256020766676",
      "rate": "1977.98753506",
      "shardTiers": [
        "WETH-USDC-Large",
        "USDC-DAI-Large"
      ],
      "txHash": "0x2a7444e97786602f0422b1a8134b8a4b5e65ffa617a6f140d88154ed136bddb2"
    },
    {
      "label": "DAI→USDC→WETH",
      "direction": "DAI→USDC→WETH",
      "mode": "multi-hop",
      "amountOut": "1.0",
      "amountIn": "1993.493572759054230442",
      "rate": "0.00050163",
      "shardTiers": [
        "USDC-DAI-Large",
        "WETH-USDC-Large"
      ],
      "txHash": "0xad4af520b55bcf8f8c2b5d93cdefc02d1796f96d36f46e60d488825492a92352"
    },
    {
      "label": "WBTC→USDC→WETH",
      "direction": "WBTC→USDC→WETH",
      "mode": "multi-hop",
      "amountOut": "1.0",
      "amountIn": "0.03018791",
      "rate": "33.12584409",
      "shardTiers": [
        "WBTC-USDC-Medium",
        "WETH-USDC-Large"
      ],
      "txHash": "0x7a78abb52c865b52c839320f75780210bfa85dc5c3d14c969dbe439d786da4b4"
    },
    {
      "label": "WETH→USDT→USDC",
      "direction": "WETH→USDT→USDC",
      "mode": "multi-hop",
      "amountOut": "2500.0",
      "amountIn": "1.258527630882179631",
      "rate": "1986.44824210",
      "shardTiers": [
        "WETH-USDT-Large",
        "USDC-USDT-Large"
      ],
      "txHash": "0x61105d80a2e015ca05830ba2fb8b15187c11a5c8a46bbbf70019d269f81f30a6"
    }
  ],
  "testResults": {
    "passed": 36,
    "failed": 0
  },
  "deployTime": "527.6s"
}